README.rst
setup.py
Enarksh.egg-info/PKG-INFO
Enarksh.egg-info/SOURCES.txt
Enarksh.egg-info/dependency_links.txt
Enarksh.egg-info/requires.txt
Enarksh.egg-info/top_level.txt
enarksh/Bootsrap.py
enarksh/DataLayer.py
enarksh/__init__.py
enarksh/application/ControllerApplication.py
enarksh/application/EnarkshApplication.py
enarksh/application/LoggerApplication.py
enarksh/application/SpawnerApplication.py
enarksh/application/__init__.py
enarksh/command/BootstrapCommand.py
enarksh/command/ControllerCommand.py
enarksh/command/DaemonCommand.py
enarksh/command/LoadHostCommand.py
enarksh/command/LoadScheduleCommand.py
enarksh/command/LoggerCommand.py
enarksh/command/NagiosCommand.py
enarksh/command/NodeActionCommand.py
enarksh/command/SpawnerCommand.py
enarksh/command/__init__.py
enarksh/controller/Controller.py
enarksh/controller/Schedule.py
enarksh/controller/StateChange.py
enarksh/controller/__init__.py
enarksh/controller/client/LoadHostClient.py
enarksh/controller/client/LoadScheduleClient.py
enarksh/controller/client/NagiosClient.py
enarksh/controller/client/NodeActionClient.py
enarksh/controller/client/__init__.py
enarksh/controller/consumption/Consumption.py
enarksh/controller/consumption/CountingConsumption.py
enarksh/controller/consumption/ReadWriteLockConsumption.py
enarksh/controller/consumption/__init__.py
enarksh/controller/event_handler/DynamicWorkerDefinitionMessageEventHandler.py
enarksh/controller/event_handler/EventQueueEmptyEventHandler.py
enarksh/controller/event_handler/JobFinishedMessageEventHandler.py
enarksh/controller/event_handler/MailOperatorEventHandler.py
enarksh/controller/event_handler/NagiosMessageEventHandler.py
enarksh/controller/event_handler/NodeActionMessageBaseEventHandler.py
enarksh/controller/event_handler/NodeActionMessageEventHandler.py
enarksh/controller/event_handler/NodeActionMessageWebEventHandler.py
enarksh/controller/event_handler/PossibleNodeActionsWebMessageEventHandler.py
enarksh/controller/event_handler/ScheduleDefinitionMessageEventHandler.py
enarksh/controller/event_handler/__init__.py
enarksh/controller/message/DynamicWorkerDefinitionMessage.py
