Metadata-Version: 1.1
Name: Enarksh
Version: 0.9.0
Summary: A lightweight and powerful job scheduler
Home-page: https://github.com/SetBased/py-enarksh
Author: Set Based IT Consultancy
Author-email: info@setbased.nl
License: MIT
Keywords: job,scheduler
Platform: UNKNOWN
Classifier: Development Status :: 3 - Alpha
Classifier: Intended Audience :: Developers
Classifier: Topic :: Software Development :: Build Tools
Classifier: Topic :: Software Development :: Code Generators
Classifier: Topic :: System :: Installation/Setup
Classifier: License :: OSI Approved :: MIT License
Classifier: Programming Language :: Python :: 3
Classifier: Programming Language :: Python :: 3.3
Classifier: Programming Language :: Python :: 3.4
Classifier: Programming Language :: Python :: 3.5
